KPHMMER/__init__.py
KPHMMER/analysis.py
KPHMMER/argument_parser.py
KPHMMER/config.py
KPHMMER/config_file_manager.py
KPHMMER/convert.py
KPHMMER/query.py
KPHMMER/search.py
KPHMMER/util.py
KPHMMER/config_files/config.yml
KPHMMER/config_files/config.yml-dist
KPHMMER/config_files/help_message.yml
KPHMMER-1.0.1.data/scripts/kphmmer
KPHMMER-1.0.1.dist-info/DESCRIPTION.rst
KPHMMER-1.0.1.dist-info/METADATA
KPHMMER-1.0.1.dist-info/RECORD
KPHMMER-1.0.1.dist-info/WHEEL
KPHMMER-1.0.1.dist-info/metadata.json
KPHMMER-1.0.1.dist-info/top_level.txt
