Metadata-Version: 2.0
Name: KPHMMER
Version: 1.0.1
Summary: KPHMMER: Hidden Markov Model generator for detecting KEGG PATHWAY-specific genes
Home-page: UNKNOWN
Author: Hirotaka Suetake
Author-email: hirotaka.suetake@riken.jp
License: MIT
Keywords: Life Science,Bioinfomatics,HMMER,KEGG
Platform: UNKNOWN
Classifier: Development Status :: 5 - Production/Stable
Classifier: Intended Audience :: Science/Research
Classifier: License :: OSI Approved :: MIT License
Classifier: Programming Language :: Python :: 3 :: Only
Classifier: Topic :: Scientific/Engineering :: Bio-Informatics
Requires-Dist: numpy
Requires-Dist: PyYAML
Requires-Dist: scipy
Requires-Dist: requests
